augmax/__init__.py
augmax/base.py
augmax/colorspace.py
augmax/functional/__init__.py
augmax/functional/colorspace.py
augmax/geometric.py
augmax/imagelevel.py
augmax/optimized.py
augmax/utils.py
augmax-0.4.0.dist-info/WHEEL
augmax-0.4.0.dist-info/METADATA
augmax-0.4.0.dist-info/RECORD
