Metadata-Version: 2.4
Name: augmax
Version: 0.4.0
Summary: Efficiently Composable Data Augmentation on the GPU with Jax
Author: Konrad Heidler
Author-email: Konrad Heidler <k.heidler@tum.de>
License-Expression: Apache-2.0
Classifier: Programming Language :: Python :: 3.9
Classifier: Programming Language :: Python :: 3.10
Classifier: Programming Language :: Python :: 3.11
Classifier: Programming Language :: Python :: 3.12
Classifier: Programming Language :: Python :: 3.13
Classifier: Programming Language :: Python :: 3.14
Classifier: Development Status :: 4 - Beta
Classifier: Intended Audience :: Science/Research
Classifier: License :: OSI Approved :: Apache Software License
Requires-Dist: einops>=0.3
Requires-Dist: jax>=0.1
Requires-Dist: numpy>=2.0.0
Requires-Python: >=3.9.0
Project-URL: Documentation, https://augmax.readthedocs.io/en/latest/
Project-URL: Issues, https://github.com/khdlr/augmax/issues
Project-URL: Repository, https://github.com/khdlr/augmax
